{
  "baseUrl": "http://127.0.0.1:5174",
  "capturedAt": "2026-05-13T01:55:04.639Z",
  "pages": [
    {
      "slug": "home",
      "path": "/",
      "label": "Home"
    },
    {
      "slug": "about-dr-carlos-brugiati",
      "path": "/dr-carlos-brugiati",
      "label": "About Dr. Carlos Brugiati"
    },
    {
      "slug": "especialidades",
      "path": "/especialidades",
      "label": "Especialidades"
    },
    {
      "slug": "agendar-cita",
      "path": "/agendar-cita",
      "label": "Agendar cita"
    },
    {
      "slug": "calculos-renales",
      "path": "/calculos-renales",
      "label": "Calculos renales"
    },
    {
      "slug": "prostata",
      "path": "/prostata",
      "label": "Prostata"
    },
    {
      "slug": "uro-oncologia",
      "path": "/uro-oncologia",
      "label": "Uro-oncologia"
    },
    {
      "slug": "endourologia",
      "path": "/endourologia",
      "label": "Endourologia"
    },
    {
      "slug": "cirugia-laparoscopica",
      "path": "/cirugia-laparoscopica",
      "label": "Cirugia laparoscopica"
    },
    {
      "slug": "salud-masculina",
      "path": "/salud-masculina",
      "label": "Salud masculina"
    },
    {
      "slug": "segunda-opinion",
      "path": "/segunda-opinion",
      "label": "Segunda opinion"
    },
    {
      "slug": "ureteroscopia",
      "path": "/ureteroscopia",
      "label": "Ureteroscopia"
    },
    {
      "slug": "laser-calculos-renales",
      "path": "/laser-calculos-renales",
      "label": "Laser calculos renales"
    },
    {
      "slug": "biopsia-prostata",
      "path": "/biopsia-prostata",
      "label": "Biopsia prostata"
    },
    {
      "slug": "nefrolitotomia-percutanea",
      "path": "/nefrolitotomia-percutanea",
      "label": "Nefrolitotomia percutanea"
    },
    {
      "slug": "cistoscopia",
      "path": "/cistoscopia",
      "label": "Cistoscopia"
    },
    {
      "slug": "cirugia-laparoscopica-renal",
      "path": "/cirugia-laparoscopica-renal",
      "label": "Cirugia laparoscopica renal"
    },
    {
      "slug": "holep",
      "path": "/holep",
      "label": "HoLEP"
    },
    {
      "slug": "rtup",
      "path": "/rtup",
      "label": "RTUP"
    },
    {
      "slug": "adenectomia-prostatica",
      "path": "/adenectomia-prostatica",
      "label": "Adenectomia prostatica"
    },
    {
      "slug": "ureteroscopia-flexible",
      "path": "/ureteroscopia-flexible",
      "label": "Ureteroscopia flexible"
    },
    {
      "slug": "ureteroscopia-semirrigida",
      "path": "/ureteroscopia-semirrigida",
      "label": "Ureteroscopia semirrigida"
    },
    {
      "slug": "litotricia-extracorporea",
      "path": "/litotricia-extracorporea",
      "label": "Litotricia extracorporea"
    },
    {
      "slug": "disfuncion-erectil",
      "path": "/disfuncion-erectil",
      "label": "Disfuncion erectil"
    },
    {
      "slug": "vasectomia",
      "path": "/vasectomia",
      "label": "Vasectomia"
    },
    {
      "slug": "privacidad",
      "path": "/privacidad",
      "label": "Privacidad"
    },
    {
      "slug": "terminos",
      "path": "/terminos",
      "label": "Terminos"
    },
    {
      "slug": "not-found",
      "path": "/pagina-no-existe",
      "label": "404 / Not found"
    }
  ],
  "viewports": [
    {
      "name": "desktop",
      "width": 1440,
      "height": 1100
    },
    {
      "name": "tablet",
      "width": 820,
      "height": 1180
    },
    {
      "name": "mobile",
      "width": 390,
      "height": 900
    }
  ],
  "screenshots": [
    {
      "label": "Home",
      "route": "/",
      "viewport": "desktop",
      "width": 1440,
      "height": 1100,
      "screenshot": "screenshots/desktop/home-desktop.jpg",
      "title": "Dr. Carlos Brugiati | Urólogo en Panamá | UroPanama",
      "h1": "Urología avanzada y cirugía mínimamente invasiva en Panamá",
      "description": "Atención urológica especializada en Panamá con enfoque en próstata, cálculos renales, uro-oncología, endourología y cirugía mínimamente invasiva.",
      "bodyHeight": 12488,
      "horizontalOverflowPx": 0
    },
    {
      "label": "About Dr. Carlos Brugiati",
      "route": "/dr-carlos-brugiati",
      "viewport": "desktop",
      "width": 1440,
      "height": 1100,
      "screenshot": "screenshots/desktop/about-dr-carlos-brugiati-desktop.jpg",
      "title": "Dr. Carlos A. Brugiati | Urología, Uro-oncología y Mínima Invasión",
      "h1": "Dr. Carlos A. Brugiati",
      "description": "Conozca el enfoque médico del Dr. Carlos A. Brugiati en urología, uro-oncología, endourología y cirugía mínimamente invasiva en Panamá.",
      "bodyHeight": 4513,
      "horizontalOverflowPx": 0
    },
    {
      "label": "Especialidades",
      "route": "/especialidades",
      "viewport": "desktop",
      "width": 1440,
      "height": 1100,
      "screenshot": "screenshots/desktop/especialidades-desktop.jpg",
      "title": "Especialidades Urológicas en Panamá | UroPanama",
      "h1": "Especialidades urológicas",
      "description": "Orientación sobre especialidades urológicas para próstata, riñón, vías urinarias, uro-oncología, endourología y salud masculina.",
      "bodyHeight": 3942,
      "horizontalOverflowPx": 0
    },
    {
      "label": "Agendar cita",
      "route": "/agendar-cita",
      "viewport": "desktop",
      "width": 1440,
      "height": 1100,
      "screenshot": "screenshots/desktop/agendar-cita-desktop.jpg",
      "title": "Agendar cita con urólogo en Panamá | Dr. Carlos Brugiati",
      "h1": "Agendar cita",
      "description": "Coordine una evaluación urológica especializada con el Dr. Carlos A. Brugiati en Ciudad de Panamá.",
      "bodyHeight": 4301,
      "horizontalOverflowPx": 0
    },
    {
      "label": "Calculos renales",
      "route": "/calculos-renales",
      "viewport": "desktop",
      "width": 1440,
      "height": 1100,
      "screenshot": "screenshots/desktop/calculos-renales-desktop.jpg",
      "title": "Cálculos renales en Panamá | Evaluación urológica especializada",
      "h1": "Cálculos renales",
      "description": "Información educativa sobre evaluación de cálculos renales, síntomas, estudios y opciones de manejo según cada caso.",
      "bodyHeight": 4925,
      "horizontalOverflowPx": 0
    },
    {
      "label": "Prostata",
      "route": "/prostata",
      "viewport": "desktop",
      "width": 1440,
      "height": 1100,
      "screenshot": "screenshots/desktop/prostata-desktop.jpg",
      "title": "Evaluación de próstata en Panamá | Dr. Carlos Brugiati",
      "h1": "Próstata",
      "description": "Evaluación médica de síntomas prostáticos, PSA elevado, crecimiento prostático y seguimiento preventivo según cada caso.",
      "bodyHeight": 4794,
      "horizontalOverflowPx": 0
    },
    {
      "label": "Uro-oncologia",
      "route": "/uro-oncologia",
      "viewport": "desktop",
      "width": 1440,
      "height": 1100,
      "screenshot": "screenshots/desktop/uro-oncologia-desktop.jpg",
      "title": "Uro-oncología en Panamá | Evaluación especializada",
      "h1": "Uro-oncología",
      "description": "Evaluación especializada de sospechas, diagnósticos o seguimiento relacionado con cáncer urológico, con lenguaje claro y seguro.",
      "bodyHeight": 4794,
      "horizontalOverflowPx": 0
    },
    {
      "label": "Endourologia",
      "route": "/endourologia",
      "viewport": "desktop",
      "width": 1440,
      "height": 1100,
      "screenshot": "screenshots/desktop/endourologia-desktop.jpg",
      "title": "Endourología en Panamá | Procedimientos mínimamente invasivos",
      "h1": "Endourología",
      "description": "Orientación sobre endourología y procedimientos mínimamente invasivos para condiciones seleccionadas de las vías urinarias.",
      "bodyHeight": 4819,
      "horizontalOverflowPx": 0
    },
    {
      "label": "Cirugia laparoscopica",
      "route": "/cirugia-laparoscopica",
      "viewport": "desktop",
      "width": 1440,
      "height": 1100,
      "screenshot": "screenshots/desktop/cirugia-laparoscopica-desktop.jpg",
      "title": "Cirugía laparoscópica urológica en Panamá | Dr. Carlos Brugiati",
      "h1": "Cirugía laparoscópica",
      "description": "Información sobre cirugía laparoscópica urológica, evaluación previa y conversación médica antes de decidir próximos pasos.",
      "bodyHeight": 5021,
      "horizontalOverflowPx": 0
    },
    {
      "label": "Salud masculina",
      "route": "/salud-masculina",
      "viewport": "desktop",
      "width": 1440,
      "height": 1100,
      "screenshot": "screenshots/desktop/salud-masculina-desktop.jpg",
      "title": "Salud urológica masculina en Panamá | Consulta privada",
      "h1": "Salud urológica masculina",
      "description": "Consulta privada para salud urológica masculina, función sexual, fertilidad, síntomas urinarios y prevención.",
      "bodyHeight": 4798,
      "horizontalOverflowPx": 0
    },
    {
      "label": "Segunda opinion",
      "route": "/segunda-opinion",
      "viewport": "desktop",
      "width": 1440,
      "height": 1100,
      "screenshot": "screenshots/desktop/segunda-opinion-desktop.jpg",
      "title": "Segunda opinión urológica en Panamá | Dr. Carlos Brugiati",
      "h1": "Segunda opinión urológica",
      "description": "Revisión de estudios, diagnósticos previos o recomendaciones quirúrgicas para orientar decisiones médicas con claridad.",
      "bodyHeight": 6153,
      "horizontalOverflowPx": 0
    },
    {
      "label": "Ureteroscopia",
      "route": "/ureteroscopia",
      "viewport": "desktop",
      "width": 1440,
      "height": 1100,
      "screenshot": "screenshots/desktop/ureteroscopia-desktop.jpg",
      "title": "Ureteroscopía en Panamá | Procedimiento urológico especializado",
      "h1": "Ureteroscopía",
      "description": "Guía educativa sobre ureteroscopía, cuándo puede considerarse, preparación general y seguimiento según evaluación médica.",
      "bodyHeight": 4430,
      "horizontalOverflowPx": 0
    },
    {
      "label": "Laser calculos renales",
      "route": "/laser-calculos-renales",
      "viewport": "desktop",
      "width": 1440,
      "height": 1100,
      "screenshot": "screenshots/desktop/laser-calculos-renales-desktop.jpg",
      "title": "Láser para cálculos urinarios en Panamá | UroPanama",
      "h1": "Láser para cálculos urinarios",
      "description": "Información educativa sobre uso de láser para cálculos urinarios, evaluación previa y seguimiento según cada caso.",
      "bodyHeight": 4430,
      "horizontalOverflowPx": 0
    },
    {
      "label": "Biopsia prostata",
      "route": "/biopsia-prostata",
      "viewport": "desktop",
      "width": 1440,
      "height": 1100,
      "screenshot": "screenshots/desktop/biopsia-prostata-desktop.jpg",
      "title": "Biopsia de próstata en Panamá | Evaluación especializada",
      "h1": "Biopsia de próstata",
      "description": "Información sobre biopsia de próstata, cuándo puede indicarse y qué estudios se revisan antes de decidir.",
      "bodyHeight": 4318,
      "horizontalOverflowPx": 0
    },
    {
      "label": "Nefrolitotomia percutanea",
      "route": "/nefrolitotomia-percutanea",
      "viewport": "desktop",
      "width": 1440,
      "height": 1100,
      "screenshot": "screenshots/desktop/nefrolitotomia-percutanea-desktop.jpg",
      "title": "Nefrolitotomía percutánea en Panamá | Cálculos complejos",
      "h1": "Nefrolitotomía percutánea",
      "description": "Orientación sobre nefrolitotomía percutánea para ciertos cálculos renales grandes o complejos según evaluación médica.",
      "bodyHeight": 4410,
      "horizontalOverflowPx": 0
    },
    {
      "label": "Cistoscopia",
      "route": "/cistoscopia",
      "viewport": "desktop",
      "width": 1440,
      "height": 1100,
      "screenshot": "screenshots/desktop/cistoscopia-desktop.jpg",
      "title": "Cistoscopía en Panamá | Evaluación de vejiga",
      "h1": "Cistoscopía",
      "description": "Información sobre cistoscopía para evaluación visual de vejiga y vías urinarias bajas en casos seleccionados.",
      "bodyHeight": 4318,
      "horizontalOverflowPx": 0
    },
    {
      "label": "Cirugia laparoscopica renal",
      "route": "/cirugia-laparoscopica-renal",
      "viewport": "desktop",
      "width": 1440,
      "height": 1100,
      "screenshot": "screenshots/desktop/cirugia-laparoscopica-renal-desktop.jpg",
      "title": "Cirugía laparoscópica renal en Panamá | Dr. Carlos Brugiati",
      "h1": "Cirugía laparoscópica renal",
      "description": "Información sobre cirugía laparoscópica renal y evaluación quirúrgica mínimamente invasiva según cada caso.",
      "bodyHeight": 4370,
      "horizontalOverflowPx": 0
    },
    {
      "label": "HoLEP",
      "route": "/holep",
      "viewport": "desktop",
      "width": 1440,
      "height": 1100,
      "screenshot": "screenshots/desktop/holep-desktop.jpg",
      "title": "HoLEP en Panamá | Enucleación prostática con láser",
      "h1": "HoLEP",
      "description": "Información sobre HoLEP o enucleación prostática con láser de Holmio para crecimiento prostático benigno y síntomas urinarios.",
      "bodyHeight": 4418,
      "horizontalOverflowPx": 0
    },
    {
      "label": "RTUP",
      "route": "/rtup",
      "viewport": "desktop",
      "width": 1440,
      "height": 1100,
      "screenshot": "screenshots/desktop/rtup-desktop.jpg",
      "title": "RTUP en Panamá | Resección transuretral de próstata",
      "h1": "RTUP",
      "description": "Guía educativa sobre RTUP para hiperplasia prostática benigna, obstrucción urinaria y síntomas prostáticos.",
      "bodyHeight": 4342,
      "horizontalOverflowPx": 0
    },
    {
      "label": "Adenectomia prostatica",
      "route": "/adenectomia-prostatica",
      "viewport": "desktop",
      "width": 1440,
      "height": 1100,
      "screenshot": "screenshots/desktop/adenectomia-prostatica-desktop.jpg",
      "title": "Adenectomía prostática laparoscópica o robótica en Panamá",
      "h1": "Adenectomía prostática",
      "description": "Información sobre adenectomía prostática laparoscópica o con asistencia robótica para próstatas grandes con obstrucción urinaria.",
      "bodyHeight": 4410,
      "horizontalOverflowPx": 0
    },
    {
      "label": "Ureteroscopia flexible",
      "route": "/ureteroscopia-flexible",
      "viewport": "desktop",
      "width": 1440,
      "height": 1100,
      "screenshot": "screenshots/desktop/ureteroscopia-flexible-desktop.jpg",
      "title": "Ureteroscopia flexible en Panamá | Cirugía intrarrenal",
      "h1": "Ureteroscopia flexible",
      "description": "Información sobre ureteroscopia flexible o cirugía endoscópica intrarrenal para cálculos renales sin incisiones externas.",
      "bodyHeight": 4390,
      "horizontalOverflowPx": 0
    },
    {
      "label": "Ureteroscopia semirrigida",
      "route": "/ureteroscopia-semirrigida",
      "viewport": "desktop",
      "width": 1440,
      "height": 1100,
      "screenshot": "screenshots/desktop/ureteroscopia-semirrigida-desktop.jpg",
      "title": "Ureteroscopia semirrígida en Panamá | Cálculos en uréter",
      "h1": "Ureteroscopia semirrígida",
      "description": "Información sobre ureteroscopia semirrígida para cálculos ubicados en el uréter y obstrucciones urinarias.",
      "bodyHeight": 4382,
      "horizontalOverflowPx": 0
    },
    {
      "label": "Litotricia extracorporea",
      "route": "/litotricia-extracorporea",
      "viewport": "desktop",
      "width": 1440,
      "height": 1100,
      "screenshot": "screenshots/desktop/litotricia-extracorporea-desktop.jpg",
      "title": "Litotricia extracorpórea en Panamá | Ondas de choque",
      "h1": "Litotricia extracorpórea",
      "description": "Información sobre litotricia extracorpórea con ondas de choque para ciertos cálculos urinarios pequeños o medianos.",
      "bodyHeight": 4386,
      "horizontalOverflowPx": 0
    },
    {
      "label": "Disfuncion erectil",
      "route": "/disfuncion-erectil",
      "viewport": "desktop",
      "width": 1440,
      "height": 1100,
      "screenshot": "screenshots/desktop/disfuncion-erectil-desktop.jpg",
      "title": "Disfunción eréctil en Panamá | Evaluación urológica privada",
      "h1": "Disfunción eréctil",
      "description": "Evaluación integral y privada de disfunción eréctil, con revisión hormonal, vascular, metabólica y opciones personalizadas.",
      "bodyHeight": 4366,
      "horizontalOverflowPx": 0
    },
    {
      "label": "Vasectomia",
      "route": "/vasectomia",
      "viewport": "desktop",
      "width": 1440,
      "height": 1100,
      "screenshot": "screenshots/desktop/vasectomia-desktop.jpg",
      "title": "Vasectomía en Panamá | Anticoncepción masculina permanente",
      "h1": "Vasectomía",
      "description": "Información sobre vasectomía como método anticonceptivo masculino permanente, ambulatorio y con seguimiento posterior.",
      "bodyHeight": 4366,
      "horizontalOverflowPx": 0
    },
    {
      "label": "Privacidad",
      "route": "/privacidad",
      "viewport": "desktop",
      "width": 1440,
      "height": 1100,
      "screenshot": "screenshots/desktop/privacidad-desktop.jpg",
      "title": "Privacidad | UroPanama",
      "h1": "Privacidad",
      "description": "Información general sobre el uso de datos enviados por formularios y canales digitales para coordinar citas urológicas.",
      "bodyHeight": 1999,
      "horizontalOverflowPx": 0
    },
    {
      "label": "Terminos",
      "route": "/terminos",
      "viewport": "desktop",
      "width": 1440,
      "height": 1100,
      "screenshot": "screenshots/desktop/terminos-desktop.jpg",
      "title": "Términos de uso | UroPanama",
      "h1": "Términos de uso",
      "description": "Condiciones generales de uso del sitio web de UroPanama y recordatorios de seguridad médica.",
      "bodyHeight": 1967,
      "horizontalOverflowPx": 0
    },
    {
      "label": "404 / Not found",
      "route": "/pagina-no-existe",
      "viewport": "desktop",
      "width": 1440,
      "height": 1100,
      "screenshot": "screenshots/desktop/not-found-desktop.jpg",
      "title": "Página no encontrada | UroPanama",
      "h1": "Página no encontrada",
      "description": "La página solicitada no está disponible. Puede volver al inicio o coordinar una consulta urológica.",
      "bodyHeight": 1373,
      "horizontalOverflowPx": 0
    },
    {
      "label": "Home",
      "route": "/",
      "viewport": "tablet",
      "width": 820,
      "height": 1180,
      "screenshot": "screenshots/tablet/home-tablet.jpg",
      "title": "Dr. Carlos Brugiati | Urólogo en Panamá | UroPanama",
      "h1": "Urología avanzada y cirugía mínimamente invasiva en Panamá",
      "description": "Atención urológica especializada en Panamá con enfoque en próstata, cálculos renales, uro-oncología, endourología y cirugía mínimamente invasiva.",
      "bodyHeight": 20633,
      "horizontalOverflowPx": 0
    },
    {
      "label": "About Dr. Carlos Brugiati",
      "route": "/dr-carlos-brugiati",
      "viewport": "tablet",
      "width": 820,
      "height": 1180,
      "screenshot": "screenshots/tablet/about-dr-carlos-brugiati-tablet.jpg",
      "title": "Dr. Carlos A. Brugiati | Urología, Uro-oncología y Mínima Invasión",
      "h1": "Dr. Carlos A. Brugiati",
      "description": "Conozca el enfoque médico del Dr. Carlos A. Brugiati en urología, uro-oncología, endourología y cirugía mínimamente invasiva en Panamá.",
      "bodyHeight": 7358,
      "horizontalOverflowPx": 0
    },
    {
      "label": "Especialidades",
      "route": "/especialidades",
      "viewport": "tablet",
      "width": 820,
      "height": 1180,
      "screenshot": "screenshots/tablet/especialidades-tablet.jpg",
      "title": "Especialidades Urológicas en Panamá | UroPanama",
      "h1": "Especialidades urológicas",
      "description": "Orientación sobre especialidades urológicas para próstata, riñón, vías urinarias, uro-oncología, endourología y salud masculina.",
      "bodyHeight": 5353,
      "horizontalOverflowPx": 0
    },
    {
      "label": "Agendar cita",
      "route": "/agendar-cita",
      "viewport": "tablet",
      "width": 820,
      "height": 1180,
      "screenshot": "screenshots/tablet/agendar-cita-tablet.jpg",
      "title": "Agendar cita con urólogo en Panamá | Dr. Carlos Brugiati",
      "h1": "Agendar cita",
      "description": "Coordine una evaluación urológica especializada con el Dr. Carlos A. Brugiati en Ciudad de Panamá.",
      "bodyHeight": 6839,
      "horizontalOverflowPx": 0
    },
    {
      "label": "Calculos renales",
      "route": "/calculos-renales",
      "viewport": "tablet",
      "width": 820,
      "height": 1180,
      "screenshot": "screenshots/tablet/calculos-renales-tablet.jpg",
      "title": "Cálculos renales en Panamá | Evaluación urológica especializada",
      "h1": "Cálculos renales",
      "description": "Información educativa sobre evaluación de cálculos renales, síntomas, estudios y opciones de manejo según cada caso.",
      "bodyHeight": 6863,
      "horizontalOverflowPx": 0
    },
    {
      "label": "Prostata",
      "route": "/prostata",
      "viewport": "tablet",
      "width": 820,
      "height": 1180,
      "screenshot": "screenshots/tablet/prostata-tablet.jpg",
      "title": "Evaluación de próstata en Panamá | Dr. Carlos Brugiati",
      "h1": "Próstata",
      "description": "Evaluación médica de síntomas prostáticos, PSA elevado, crecimiento prostático y seguimiento preventivo según cada caso.",
      "bodyHeight": 6784,
      "horizontalOverflowPx": 0
    },
    {
      "label": "Uro-oncologia",
      "route": "/uro-oncologia",
      "viewport": "tablet",
      "width": 820,
      "height": 1180,
      "screenshot": "screenshots/tablet/uro-oncologia-tablet.jpg",
      "title": "Uro-oncología en Panamá | Evaluación especializada",
      "h1": "Uro-oncología",
      "description": "Evaluación especializada de sospechas, diagnósticos o seguimiento relacionado con cáncer urológico, con lenguaje claro y seguro.",
      "bodyHeight": 6752,
      "horizontalOverflowPx": 0
    },
    {
      "label": "Endourologia",
      "route": "/endourologia",
      "viewport": "tablet",
      "width": 820,
      "height": 1180,
      "screenshot": "screenshots/tablet/endourologia-tablet.jpg",
      "title": "Endourología en Panamá | Procedimientos mínimamente invasivos",
      "h1": "Endourología",
      "description": "Orientación sobre endourología y procedimientos mínimamente invasivos para condiciones seleccionadas de las vías urinarias.",
      "bodyHeight": 6808,
      "horizontalOverflowPx": 0
    },
    {
      "label": "Cirugia laparoscopica",
      "route": "/cirugia-laparoscopica",
      "viewport": "tablet",
      "width": 820,
      "height": 1180,
      "screenshot": "screenshots/tablet/cirugia-laparoscopica-tablet.jpg",
      "title": "Cirugía laparoscópica urológica en Panamá | Dr. Carlos Brugiati",
      "h1": "Cirugía laparoscópica",
      "description": "Información sobre cirugía laparoscópica urológica, evaluación previa y conversación médica antes de decidir próximos pasos.",
      "bodyHeight": 6988,
      "horizontalOverflowPx": 0
    },
    {
      "label": "Salud masculina",
      "route": "/salud-masculina",
      "viewport": "tablet",
      "width": 820,
      "height": 1180,
      "screenshot": "screenshots/tablet/salud-masculina-tablet.jpg",
      "title": "Salud urológica masculina en Panamá | Consulta privada",
      "h1": "Salud urológica masculina",
      "description": "Consulta privada para salud urológica masculina, función sexual, fertilidad, síntomas urinarios y prevención.",
      "bodyHeight": 6838,
      "horizontalOverflowPx": 0
    },
    {
      "label": "Segunda opinion",
      "route": "/segunda-opinion",
      "viewport": "tablet",
      "width": 820,
      "height": 1180,
      "screenshot": "screenshots/tablet/segunda-opinion-tablet.jpg",
      "title": "Segunda opinión urológica en Panamá | Dr. Carlos Brugiati",
      "h1": "Segunda opinión urológica",
      "description": "Revisión de estudios, diagnósticos previos o recomendaciones quirúrgicas para orientar decisiones médicas con claridad.",
      "bodyHeight": 8830,
      "horizontalOverflowPx": 0
    },
    {
      "label": "Ureteroscopia",
      "route": "/ureteroscopia",
      "viewport": "tablet",
      "width": 820,
      "height": 1180,
      "screenshot": "screenshots/tablet/ureteroscopia-tablet.jpg",
      "title": "Ureteroscopía en Panamá | Procedimiento urológico especializado",
      "h1": "Ureteroscopía",
      "description": "Guía educativa sobre ureteroscopía, cuándo puede considerarse, preparación general y seguimiento según evaluación médica.",
      "bodyHeight": 6402,
      "horizontalOverflowPx": 0
    },
    {
      "label": "Laser calculos renales",
      "route": "/laser-calculos-renales",
      "viewport": "tablet",
      "width": 820,
      "height": 1180,
      "screenshot": "screenshots/tablet/laser-calculos-renales-tablet.jpg",
      "title": "Láser para cálculos urinarios en Panamá | UroPanama",
      "h1": "Láser para cálculos urinarios",
      "description": "Información educativa sobre uso de láser para cálculos urinarios, evaluación previa y seguimiento según cada caso.",
      "bodyHeight": 6474,
      "horizontalOverflowPx": 0
    },
    {
      "label": "Biopsia prostata",
      "route": "/biopsia-prostata",
      "viewport": "tablet",
      "width": 820,
      "height": 1180,
      "screenshot": "screenshots/tablet/biopsia-prostata-tablet.jpg",
      "title": "Biopsia de próstata en Panamá | Evaluación especializada",
      "h1": "Biopsia de próstata",
      "description": "Información sobre biopsia de próstata, cuándo puede indicarse y qué estudios se revisan antes de decidir.",
      "bodyHeight": 6374,
      "horizontalOverflowPx": 0
    },
    {
      "label": "Nefrolitotomia percutanea",
      "route": "/nefrolitotomia-percutanea",
      "viewport": "tablet",
      "width": 820,
      "height": 1180,
      "screenshot": "screenshots/tablet/nefrolitotomia-percutanea-tablet.jpg",
      "title": "Nefrolitotomía percutánea en Panamá | Cálculos complejos",
      "h1": "Nefrolitotomía percutánea",
      "description": "Orientación sobre nefrolitotomía percutánea para ciertos cálculos renales grandes o complejos según evaluación médica.",
      "bodyHeight": 6474,
      "horizontalOverflowPx": 0
    },
    {
      "label": "Cistoscopia",
      "route": "/cistoscopia",
      "viewport": "tablet",
      "width": 820,
      "height": 1180,
      "screenshot": "screenshots/tablet/cistoscopia-tablet.jpg",
      "title": "Cistoscopía en Panamá | Evaluación de vejiga",
      "h1": "Cistoscopía",
      "description": "Información sobre cistoscopía para evaluación visual de vejiga y vías urinarias bajas en casos seleccionados.",
      "bodyHeight": 6374,
      "horizontalOverflowPx": 0
    },
    {
      "label": "Cirugia laparoscopica renal",
      "route": "/cirugia-laparoscopica-renal",
      "viewport": "tablet",
      "width": 820,
      "height": 1180,
      "screenshot": "screenshots/tablet/cirugia-laparoscopica-renal-tablet.jpg",
      "title": "Cirugía laparoscópica renal en Panamá | Dr. Carlos Brugiati",
      "h1": "Cirugía laparoscópica renal",
      "description": "Información sobre cirugía laparoscópica renal y evaluación quirúrgica mínimamente invasiva según cada caso.",
      "bodyHeight": 6474,
      "horizontalOverflowPx": 0
    },
    {
      "label": "HoLEP",
      "route": "/holep",
      "viewport": "tablet",
      "width": 820,
      "height": 1180,
      "screenshot": "screenshots/tablet/holep-tablet.jpg",
      "title": "HoLEP en Panamá | Enucleación prostática con láser",
      "h1": "HoLEP",
      "description": "Información sobre HoLEP o enucleación prostática con láser de Holmio para crecimiento prostático benigno y síntomas urinarios.",
      "bodyHeight": 6402,
      "horizontalOverflowPx": 0
    },
    {
      "label": "RTUP",
      "route": "/rtup",
      "viewport": "tablet",
      "width": 820,
      "height": 1180,
      "screenshot": "screenshots/tablet/rtup-tablet.jpg",
      "title": "RTUP en Panamá | Resección transuretral de próstata",
      "h1": "RTUP",
      "description": "Guía educativa sobre RTUP para hiperplasia prostática benigna, obstrucción urinaria y síntomas prostáticos.",
      "bodyHeight": 6374,
      "horizontalOverflowPx": 0
    },
    {
      "label": "Adenectomia prostatica",
      "route": "/adenectomia-prostatica",
      "viewport": "tablet",
      "width": 820,
      "height": 1180,
      "screenshot": "screenshots/tablet/adenectomia-prostatica-tablet.jpg",
      "title": "Adenectomía prostática laparoscópica o robótica en Panamá",
      "h1": "Adenectomía prostática",
      "description": "Información sobre adenectomía prostática laparoscópica o con asistencia robótica para próstatas grandes con obstrucción urinaria.",
      "bodyHeight": 6402,
      "horizontalOverflowPx": 0
    },
    {
      "label": "Ureteroscopia flexible",
      "route": "/ureteroscopia-flexible",
      "viewport": "tablet",
      "width": 820,
      "height": 1180,
      "screenshot": "screenshots/tablet/ureteroscopia-flexible-tablet.jpg",
      "title": "Ureteroscopia flexible en Panamá | Cirugía intrarrenal",
      "h1": "Ureteroscopia flexible",
      "description": "Información sobre ureteroscopia flexible o cirugía endoscópica intrarrenal para cálculos renales sin incisiones externas.",
      "bodyHeight": 6314,
      "horizontalOverflowPx": 0
    },
    {
      "label": "Ureteroscopia semirrigida",
      "route": "/ureteroscopia-semirrigida",
      "viewport": "tablet",
      "width": 820,
      "height": 1180,
      "screenshot": "screenshots/tablet/ureteroscopia-semirrigida-tablet.jpg",
      "title": "Ureteroscopia semirrígida en Panamá | Cálculos en uréter",
      "h1": "Ureteroscopia semirrígida",
      "description": "Información sobre ureteroscopia semirrígida para cálculos ubicados en el uréter y obstrucciones urinarias.",
      "bodyHeight": 6390,
      "horizontalOverflowPx": 0
    },
    {
      "label": "Litotricia extracorporea",
      "route": "/litotricia-extracorporea",
      "viewport": "tablet",
      "width": 820,
      "height": 1180,
      "screenshot": "screenshots/tablet/litotricia-extracorporea-tablet.jpg",
      "title": "Litotricia extracorpórea en Panamá | Ondas de choque",
      "h1": "Litotricia extracorpórea",
      "description": "Información sobre litotricia extracorpórea con ondas de choque para ciertos cálculos urinarios pequeños o medianos.",
      "bodyHeight": 6314,
      "horizontalOverflowPx": 0
    },
    {
      "label": "Disfuncion erectil",
      "route": "/disfuncion-erectil",
      "viewport": "tablet",
      "width": 820,
      "height": 1180,
      "screenshot": "screenshots/tablet/disfuncion-erectil-tablet.jpg",
      "title": "Disfunción eréctil en Panamá | Evaluación urológica privada",
      "h1": "Disfunción eréctil",
      "description": "Evaluación integral y privada de disfunción eréctil, con revisión hormonal, vascular, metabólica y opciones personalizadas.",
      "bodyHeight": 6370,
      "horizontalOverflowPx": 0
    },
    {
      "label": "Vasectomia",
      "route": "/vasectomia",
      "viewport": "tablet",
      "width": 820,
      "height": 1180,
      "screenshot": "screenshots/tablet/vasectomia-tablet.jpg",
      "title": "Vasectomía en Panamá | Anticoncepción masculina permanente",
      "h1": "Vasectomía",
      "description": "Información sobre vasectomía como método anticonceptivo masculino permanente, ambulatorio y con seguimiento posterior.",
      "bodyHeight": 6342,
      "horizontalOverflowPx": 0
    },
    {
      "label": "Privacidad",
      "route": "/privacidad",
      "viewport": "tablet",
      "width": 820,
      "height": 1180,
      "screenshot": "screenshots/tablet/privacidad-tablet.jpg",
      "title": "Privacidad | UroPanama",
      "h1": "Privacidad",
      "description": "Información general sobre el uso de datos enviados por formularios y canales digitales para coordinar citas urológicas.",
      "bodyHeight": 2679,
      "horizontalOverflowPx": 0
    },
    {
      "label": "Terminos",
      "route": "/terminos",
      "viewport": "tablet",
      "width": 820,
      "height": 1180,
      "screenshot": "screenshots/tablet/terminos-tablet.jpg",
      "title": "Términos de uso | UroPanama",
      "h1": "Términos de uso",
      "description": "Condiciones generales de uso del sitio web de UroPanama y recordatorios de seguridad médica.",
      "bodyHeight": 2647,
      "horizontalOverflowPx": 0
    },
    {
      "label": "404 / Not found",
      "route": "/pagina-no-existe",
      "viewport": "tablet",
      "width": 820,
      "height": 1180,
      "screenshot": "screenshots/tablet/not-found-tablet.jpg",
      "title": "Página no encontrada | UroPanama",
      "h1": "Página no encontrada",
      "description": "La página solicitada no está disponible. Puede volver al inicio o coordinar una consulta urológica.",
      "bodyHeight": 2053,
      "horizontalOverflowPx": 0
    },
    {
      "label": "Home",
      "route": "/",
      "viewport": "mobile",
      "width": 390,
      "height": 900,
      "screenshot": "screenshots/mobile/home-mobile.jpg",
      "title": "Dr. Carlos Brugiati | Urólogo en Panamá | UroPanama",
      "h1": "Urología avanzada y cirugía mínimamente invasiva en Panamá",
      "description": "Atención urológica especializada en Panamá con enfoque en próstata, cálculos renales, uro-oncología, endourología y cirugía mínimamente invasiva.",
      "bodyHeight": 27353,
      "horizontalOverflowPx": 0
    },
    {
      "label": "About Dr. Carlos Brugiati",
      "route": "/dr-carlos-brugiati",
      "viewport": "mobile",
      "width": 390,
      "height": 900,
      "screenshot": "screenshots/mobile/about-dr-carlos-brugiati-mobile.jpg",
      "title": "Dr. Carlos A. Brugiati | Urología, Uro-oncología y Mínima Invasión",
      "h1": "Dr. Carlos A. Brugiati",
      "description": "Conozca el enfoque médico del Dr. Carlos A. Brugiati en urología, uro-oncología, endourología y cirugía mínimamente invasiva en Panamá.",
      "bodyHeight": 9289,
      "horizontalOverflowPx": 0
    },
    {
      "label": "Especialidades",
      "route": "/especialidades",
      "viewport": "mobile",
      "width": 390,
      "height": 900,
      "screenshot": "screenshots/mobile/especialidades-mobile.jpg",
      "title": "Especialidades Urológicas en Panamá | UroPanama",
      "h1": "Especialidades urológicas",
      "description": "Orientación sobre especialidades urológicas para próstata, riñón, vías urinarias, uro-oncología, endourología y salud masculina.",
      "bodyHeight": 7221,
      "horizontalOverflowPx": 0
    },
    {
      "label": "Agendar cita",
      "route": "/agendar-cita",
      "viewport": "mobile",
      "width": 390,
      "height": 900,
      "screenshot": "screenshots/mobile/agendar-cita-mobile.jpg",
      "title": "Agendar cita con urólogo en Panamá | Dr. Carlos Brugiati",
      "h1": "Agendar cita",
      "description": "Coordine una evaluación urológica especializada con el Dr. Carlos A. Brugiati en Ciudad de Panamá.",
      "bodyHeight": 8364,
      "horizontalOverflowPx": 0
    },
    {
      "label": "Calculos renales",
      "route": "/calculos-renales",
      "viewport": "mobile",
      "width": 390,
      "height": 900,
      "screenshot": "screenshots/mobile/calculos-renales-mobile.jpg",
      "title": "Cálculos renales en Panamá | Evaluación urológica especializada",
      "h1": "Cálculos renales",
      "description": "Información educativa sobre evaluación de cálculos renales, síntomas, estudios y opciones de manejo según cada caso.",
      "bodyHeight": 8675,
      "horizontalOverflowPx": 0
    },
    {
      "label": "Prostata",
      "route": "/prostata",
      "viewport": "mobile",
      "width": 390,
      "height": 900,
      "screenshot": "screenshots/mobile/prostata-mobile.jpg",
      "title": "Evaluación de próstata en Panamá | Dr. Carlos Brugiati",
      "h1": "Próstata",
      "description": "Evaluación médica de síntomas prostáticos, PSA elevado, crecimiento prostático y seguimiento preventivo según cada caso.",
      "bodyHeight": 8305,
      "horizontalOverflowPx": 0
    },
    {
      "label": "Uro-oncologia",
      "route": "/uro-oncologia",
      "viewport": "mobile",
      "width": 390,
      "height": 900,
      "screenshot": "screenshots/mobile/uro-oncologia-mobile.jpg",
      "title": "Uro-oncología en Panamá | Evaluación especializada",
      "h1": "Uro-oncología",
      "description": "Evaluación especializada de sospechas, diagnósticos o seguimiento relacionado con cáncer urológico, con lenguaje claro y seguro.",
      "bodyHeight": 8452,
      "horizontalOverflowPx": 0
    },
    {
      "label": "Endourologia",
      "route": "/endourologia",
      "viewport": "mobile",
      "width": 390,
      "height": 900,
      "screenshot": "screenshots/mobile/endourologia-mobile.jpg",
      "title": "Endourología en Panamá | Procedimientos mínimamente invasivos",
      "h1": "Endourología",
      "description": "Orientación sobre endourología y procedimientos mínimamente invasivos para condiciones seleccionadas de las vías urinarias.",
      "bodyHeight": 8389,
      "horizontalOverflowPx": 0
    },
    {
      "label": "Cirugia laparoscopica",
      "route": "/cirugia-laparoscopica",
      "viewport": "mobile",
      "width": 390,
      "height": 900,
      "screenshot": "screenshots/mobile/cirugia-laparoscopica-mobile.jpg",
      "title": "Cirugía laparoscópica urológica en Panamá | Dr. Carlos Brugiati",
      "h1": "Cirugía laparoscópica",
      "description": "Información sobre cirugía laparoscópica urológica, evaluación previa y conversación médica antes de decidir próximos pasos.",
      "bodyHeight": 9064,
      "horizontalOverflowPx": 0
    },
    {
      "label": "Salud masculina",
      "route": "/salud-masculina",
      "viewport": "mobile",
      "width": 390,
      "height": 900,
      "screenshot": "screenshots/mobile/salud-masculina-mobile.jpg",
      "title": "Salud urológica masculina en Panamá | Consulta privada",
      "h1": "Salud urológica masculina",
      "description": "Consulta privada para salud urológica masculina, función sexual, fertilidad, síntomas urinarios y prevención.",
      "bodyHeight": 8430,
      "horizontalOverflowPx": 0
    },
    {
      "label": "Segunda opinion",
      "route": "/segunda-opinion",
      "viewport": "mobile",
      "width": 390,
      "height": 900,
      "screenshot": "screenshots/mobile/segunda-opinion-mobile.jpg",
      "title": "Segunda opinión urológica en Panamá | Dr. Carlos Brugiati",
      "h1": "Segunda opinión urológica",
      "description": "Revisión de estudios, diagnósticos previos o recomendaciones quirúrgicas para orientar decisiones médicas con claridad.",
      "bodyHeight": 11123,
      "horizontalOverflowPx": 0
    },
    {
      "label": "Ureteroscopia",
      "route": "/ureteroscopia",
      "viewport": "mobile",
      "width": 390,
      "height": 900,
      "screenshot": "screenshots/mobile/ureteroscopia-mobile.jpg",
      "title": "Ureteroscopía en Panamá | Procedimiento urológico especializado",
      "h1": "Ureteroscopía",
      "description": "Guía educativa sobre ureteroscopía, cuándo puede considerarse, preparación general y seguimiento según evaluación médica.",
      "bodyHeight": 7548,
      "horizontalOverflowPx": 0
    },
    {
      "label": "Laser calculos renales",
      "route": "/laser-calculos-renales",
      "viewport": "mobile",
      "width": 390,
      "height": 900,
      "screenshot": "screenshots/mobile/laser-calculos-renales-mobile.jpg",
      "title": "Láser para cálculos urinarios en Panamá | UroPanama",
      "h1": "Láser para cálculos urinarios",
      "description": "Información educativa sobre uso de láser para cálculos urinarios, evaluación previa y seguimiento según cada caso.",
      "bodyHeight": 7638,
      "horizontalOverflowPx": 0
    },
    {
      "label": "Biopsia prostata",
      "route": "/biopsia-prostata",
      "viewport": "mobile",
      "width": 390,
      "height": 900,
      "screenshot": "screenshots/mobile/biopsia-prostata-mobile.jpg",
      "title": "Biopsia de próstata en Panamá | Evaluación especializada",
      "h1": "Biopsia de próstata",
      "description": "Información sobre biopsia de próstata, cuándo puede indicarse y qué estudios se revisan antes de decidir.",
      "bodyHeight": 7469,
      "horizontalOverflowPx": 0
    },
    {
      "label": "Nefrolitotomia percutanea",
      "route": "/nefrolitotomia-percutanea",
      "viewport": "mobile",
      "width": 390,
      "height": 900,
      "screenshot": "screenshots/mobile/nefrolitotomia-percutanea-mobile.jpg",
      "title": "Nefrolitotomía percutánea en Panamá | Cálculos complejos",
      "h1": "Nefrolitotomía percutánea",
      "description": "Orientación sobre nefrolitotomía percutánea para ciertos cálculos renales grandes o complejos según evaluación médica.",
      "bodyHeight": 7369,
      "horizontalOverflowPx": 0
    },
    {
      "label": "Cistoscopia",
      "route": "/cistoscopia",
      "viewport": "mobile",
      "width": 390,
      "height": 900,
      "screenshot": "screenshots/mobile/cistoscopia-mobile.jpg",
      "title": "Cistoscopía en Panamá | Evaluación de vejiga",
      "h1": "Cistoscopía",
      "description": "Información sobre cistoscopía para evaluación visual de vejiga y vías urinarias bajas en casos seleccionados.",
      "bodyHeight": 7216,
      "horizontalOverflowPx": 0
    },
    {
      "label": "Cirugia laparoscopica renal",
      "route": "/cirugia-laparoscopica-renal",
      "viewport": "mobile",
      "width": 390,
      "height": 900,
      "screenshot": "screenshots/mobile/cirugia-laparoscopica-renal-mobile.jpg",
      "title": "Cirugía laparoscópica renal en Panamá | Dr. Carlos Brugiati",
      "h1": "Cirugía laparoscópica renal",
      "description": "Información sobre cirugía laparoscópica renal y evaluación quirúrgica mínimamente invasiva según cada caso.",
      "bodyHeight": 7356,
      "horizontalOverflowPx": 0
    },
    {
      "label": "HoLEP",
      "route": "/holep",
      "viewport": "mobile",
      "width": 390,
      "height": 900,
      "screenshot": "screenshots/mobile/holep-mobile.jpg",
      "title": "HoLEP en Panamá | Enucleación prostática con láser",
      "h1": "HoLEP",
      "description": "Información sobre HoLEP o enucleación prostática con láser de Holmio para crecimiento prostático benigno y síntomas urinarios.",
      "bodyHeight": 7530,
      "horizontalOverflowPx": 0
    },
    {
      "label": "RTUP",
      "route": "/rtup",
      "viewport": "mobile",
      "width": 390,
      "height": 900,
      "screenshot": "screenshots/mobile/rtup-mobile.jpg",
      "title": "RTUP en Panamá | Resección transuretral de próstata",
      "h1": "RTUP",
      "description": "Guía educativa sobre RTUP para hiperplasia prostática benigna, obstrucción urinaria y síntomas prostáticos.",
      "bodyHeight": 7332,
      "horizontalOverflowPx": 0
    },
    {
      "label": "Adenectomia prostatica",
      "route": "/adenectomia-prostatica",
      "viewport": "mobile",
      "width": 390,
      "height": 900,
      "screenshot": "screenshots/mobile/adenectomia-prostatica-mobile.jpg",
      "title": "Adenectomía prostática laparoscópica o robótica en Panamá",
      "h1": "Adenectomía prostática",
      "description": "Información sobre adenectomía prostática laparoscópica o con asistencia robótica para próstatas grandes con obstrucción urinaria.",
      "bodyHeight": 7563,
      "horizontalOverflowPx": 0
    },
    {
      "label": "Ureteroscopia flexible",
      "route": "/ureteroscopia-flexible",
      "viewport": "mobile",
      "width": 390,
      "height": 900,
      "screenshot": "screenshots/mobile/ureteroscopia-flexible-mobile.jpg",
      "title": "Ureteroscopia flexible en Panamá | Cirugía intrarrenal",
      "h1": "Ureteroscopia flexible",
      "description": "Información sobre ureteroscopia flexible o cirugía endoscópica intrarrenal para cálculos renales sin incisiones externas.",
      "bodyHeight": 7425,
      "horizontalOverflowPx": 0
    },
    {
      "label": "Ureteroscopia semirrigida",
      "route": "/ureteroscopia-semirrigida",
      "viewport": "mobile",
      "width": 390,
      "height": 900,
      "screenshot": "screenshots/mobile/ureteroscopia-semirrigida-mobile.jpg",
      "title": "Ureteroscopia semirrígida en Panamá | Cálculos en uréter",
      "h1": "Ureteroscopia semirrígida",
      "description": "Información sobre ureteroscopia semirrígida para cálculos ubicados en el uréter y obstrucciones urinarias.",
      "bodyHeight": 7401,
      "horizontalOverflowPx": 0
    },
    {
      "label": "Litotricia extracorporea",
      "route": "/litotricia-extracorporea",
      "viewport": "mobile",
      "width": 390,
      "height": 900,
      "screenshot": "screenshots/mobile/litotricia-extracorporea-mobile.jpg",
      "title": "Litotricia extracorpórea en Panamá | Ondas de choque",
      "h1": "Litotricia extracorpórea",
      "description": "Información sobre litotricia extracorpórea con ondas de choque para ciertos cálculos urinarios pequeños o medianos.",
      "bodyHeight": 7361,
      "horizontalOverflowPx": 0
    },
    {
      "label": "Disfuncion erectil",
      "route": "/disfuncion-erectil",
      "viewport": "mobile",
      "width": 390,
      "height": 900,
      "screenshot": "screenshots/mobile/disfuncion-erectil-mobile.jpg",
      "title": "Disfunción eréctil en Panamá | Evaluación urológica privada",
      "h1": "Disfunción eréctil",
      "description": "Evaluación integral y privada de disfunción eréctil, con revisión hormonal, vascular, metabólica y opciones personalizadas.",
      "bodyHeight": 7447,
      "horizontalOverflowPx": 0
    },
    {
      "label": "Vasectomia",
      "route": "/vasectomia",
      "viewport": "mobile",
      "width": 390,
      "height": 900,
      "screenshot": "screenshots/mobile/vasectomia-mobile.jpg",
      "title": "Vasectomía en Panamá | Anticoncepción masculina permanente",
      "h1": "Vasectomía",
      "description": "Información sobre vasectomía como método anticonceptivo masculino permanente, ambulatorio y con seguimiento posterior.",
      "bodyHeight": 7288,
      "horizontalOverflowPx": 0
    },
    {
      "label": "Privacidad",
      "route": "/privacidad",
      "viewport": "mobile",
      "width": 390,
      "height": 900,
      "screenshot": "screenshots/mobile/privacidad-mobile.jpg",
      "title": "Privacidad | UroPanama",
      "h1": "Privacidad",
      "description": "Información general sobre el uso de datos enviados por formularios y canales digitales para coordinar citas urológicas.",
      "bodyHeight": 3204,
      "horizontalOverflowPx": 0
    },
    {
      "label": "Terminos",
      "route": "/terminos",
      "viewport": "mobile",
      "width": 390,
      "height": 900,
      "screenshot": "screenshots/mobile/terminos-mobile.jpg",
      "title": "Términos de uso | UroPanama",
      "h1": "Términos de uso",
      "description": "Condiciones generales de uso del sitio web de UroPanama y recordatorios de seguridad médica.",
      "bodyHeight": 3203,
      "horizontalOverflowPx": 0
    },
    {
      "label": "404 / Not found",
      "route": "/pagina-no-existe",
      "viewport": "mobile",
      "width": 390,
      "height": 900,
      "screenshot": "screenshots/mobile/not-found-mobile.jpg",
      "title": "Página no encontrada | UroPanama",
      "h1": "Página no encontrada",
      "description": "La página solicitada no está disponible. Puede volver al inicio o coordinar una consulta urológica.",
      "bodyHeight": 2241,
      "horizontalOverflowPx": 0
    }
  ]
}